[
  {
    "id": 1,
    "name": "二次元少女",
    "platform": "QQ",
    "price": 3000,
    "publish_time": "3分钟内发布",
    "url": "https://www.pxb7.com/product/2091816594555580221/1"
  },
  {
    "id": 2,
    "name": "马龙",
    "platform": "QQ",
    "price": 900,
    "publish_time": "10分钟内发布",
    "url": "https://www.pxb7.com/product/2091807911936868522/1"
  },
  {
    "id": 3,
    "name": "湖北林俊杰",
    "platform": "QQ",
    "price": 99999,
    "publish_time": "15小时内发布",
    "url": "https://www.pxb7.com/product/2090725137777307092/1"
  },
  {
    "id": 4,
    "name": "熹妃 存心",
    "platform": "QQ",
    "price": 2000,
    "publish_time": "11分钟内发布",
    "url": "https://www.pxb7.com/product/2091806716723282164/1"
  },
  {
    "id": 5,
    "name": "小死神",
    "platform": "QQ",
    "price": 9999,
    "publish_time": "15分钟内发布",
    "url": "https://www.pxb7.com/product/2091800823480468929/1"
  },
  {
    "id": 6,
    "name": "Queen",
    "platform": "QQ",
    "price": 88888,
    "publish_time": "16小时内发布",
    "url": "https://www.pxb7.com/product/2090621223649840542/1"
  },
  {
    "id": 7,
    "name": "楚子航的猫",
    "platform": "QQ",
    "price": 100,
    "publish_time": "42分钟内发布",
    "url": "https://www.pxb7.com/product/2091767610573516847/1"
  },
  {
    "id": 8,
    "name": "手撕鸡",
    "platform": "QQ",
    "price": 3699,
    "publish_time": "42分钟内发布",
    "url": "https://www.pxb7.com/product/2091767569121687207/1"
  },
  {
    "id": 9,
    "name": "甜妹小婷",
    "platform": "QQ",
    "price": 520,
    "publish_time": "16小时内发布",
    "url": "https://www.pxb7.com/product/2090619545846467276/1"
  },
  {
    "id": 10,
    "name": "台球杆",
    "platform": "QQ",
    "price": 600,
    "publish_time": "43分钟内发布",
    "url": "https://www.pxb7.com/product/2091765660631554639/1"
  },
  {
    "id": 11,
    "name": "365872",
    "platform": "QQ",
    "price": 200,
    "publish_time": "2小时内发布",
    "url": "https://www.pxb7.com/product/2091739698135322770/1"
  },
  {
    "id": 12,
    "name": "菊",
    "platform": "QQ",
    "price": 4300,
    "publish_time": "17小时内发布",
    "url": "https://www.pxb7.com/product/2090593373634821405/1"
  },
  {
    "id": 13,
    "name": "双字ID",
    "platform": "QQ",
    "price": 600,
    "publish_time": "2小时内发布",
    "url": "https://www.pxb7.com/product/2091737873695279556/1"
  },
  {
    "id": 14,
    "name": "权·",
    "platform": "QQ",
    "price": 1500,
    "publish_time": "2小时内发布",
    "url": "https://www.pxb7.com/product/2091707527823876605/1"
  },
  {
    "id": 15,
    "name": "双",
    "platform": "微信",
    "price": 55000,
    "publish_time": "18小时内发布",
    "url": "https://www.pxb7.com/product/2090526936105053812/1"
  },
  {
    "id": 16,
    "name": "乘宝宝",
    "platform": "QQ",
    "price": 150,
    "publish_time": "2小时内发布",
    "url": "https://www.pxb7.com/product/2091680305971289660/1"
  },
  {
    "id": 17,
    "name": "萱萱姐",
    "platform": "QQ",
    "price": 188,
    "publish_time": "3小时内发布",
    "url": "https://www.pxb7.com/product/2091668226540127304/1"
  },
  {
    "id": 18,
    "name": "萌梓馨",
    "platform": "QQ",
    "price": 188,
    "publish_time": "3小时内发布",
    "url": "https://www.pxb7.com/product/2091656398602577304/1"
  },
  {
    "id": 19,
    "name": "伤风",
    "platform": "QQ",
    "price": 5000,
    "publish_time": "20小时内发布",
    "url": "https://www.pxb7.com/product/2090377408348461256/1"
  },
  {
    "id": 20,
    "name": "圣子豪",
    "platform": "QQ",
    "price": 188,
    "publish_time": "3小时内发布",
    "url": "https://www.pxb7.com/product/2091648031130177304/1"
  },
  {
    "id": 21,
    "name": "双字ID",
    "platform": "QQ",
    "price": 800,
    "publish_time": "3小时内发布",
    "url": "https://www.pxb7.com/product/2091629219758755995/1"
  },
  {
    "id": 22,
    "name": "轻重",
    "platform": "QQ",
    "price": 530,
    "publish_time": "21小时内发布",
    "url": "https://www.pxb7.com/product/2090272173671167321/1"
  },
  {
    "id": 23,
    "name": "上官•婉儿",
    "platform": "QQ",
    "price": 388,
    "publish_time": "3小时内发布",
    "url": "https://www.pxb7.com/product/2091623872430498755/1"
  },
  {
    "id": 24,
    "name": "铠•天下第一",
    "platform": "QQ",
    "price": 100,
    "publish_time": "3小时内发布",
    "url": "https://www.pxb7.com/product/2091622319800358755/1"
  },
  {
    "id": 25,
    "name": "流脉",
    "platform": "QQ",
    "price": 1666,
    "publish_time": "22小时内发布",
    "url": "https://www.pxb7.com/product/2090196130775420246/1"
  },
  {
    "id": 26,
    "name": "马可•波罗",
    "platform": "QQ",
    "price": 388,
    "publish_time": "3小时内发布",
    "url": "https://www.pxb7.com/product/2091618168176808755/1"
  },
  {
    "id": 27,
    "name": "宫本•武藏",
    "platform": "QQ",
    "price": 388,
    "publish_time": "3小时内发布",
    "url": "https://www.pxb7.com/product/2091612694692058755/1"
  },
  {
    "id": 28,
    "name": "俪",
    "platform": "QQ",
    "price": 1999,
    "publish_time": "23小时内发布",
    "url": "https://www.pxb7.com/product/2090104863048313391/1"
  },
  {
    "id": 29,
    "name": "烟波乔",
    "platform": "QQ",
    "price": 288,
    "publish_time": "3小时内发布",
    "url": "https://www.pxb7.com/product/2091599670477199389/1"
  },
  {
    "id": 30,
    "name": "月下嫦",
    "platform": "QQ",
    "price": 200,
    "publish_time": "4小时内发布",
    "url": "https://www.pxb7.com/product/2091591743897959389/1"
  },
  {
    "id": 31,
    "name": "舞娘",
    "platform": "QQ",
    "price": 600,
    "publish_time": "24小时内发布",
    "url": "https://www.pxb7.com/product/2090038508831433391/1"
  },
  {
    "id": 32,
    "name": "虘",
    "platform": "QQ",
    "price": 800,
    "publish_time": "4小时内发布",
    "url": "https://www.pxb7.com/product/2091588661084545946/1"
  },
  {
    "id": 33,
    "name": "算逑",
    "platform": "QQ",
    "price": 100,
    "publish_time": "4小时内发布",
    "url": "https://www.pxb7.com/product/2091570101371455714/1"
  },
  {
    "id": 34,
    "name": "梵古",
    "platform": "QQ",
    "price": 199,
    "publish_time": "4小时内发布",
    "url": "https://www.pxb7.com/product/2091535498527021413/1"
  },
  {
    "id": 35,
    "name": "马斯克",
    "platform": "微信",
    "price": 19999,
    "publish_time": "1天内发布",
    "url": "https://www.pxb7.com/product/2090011791524737207/1"
  },
  {
    "id": 36,
    "name": "青琢",
    "platform": "QQ",
    "price": 99,
    "publish_time": "4小时内发布",
    "url": "https://www.pxb7.com/product/2091533820560331413/1"
  },
  {
    "id": 37,
    "name": "淮一",
    "platform": "QQ",
    "price": 99,
    "publish_time": "4小时内发布",
    "url": "https://www.pxb7.com/product/2091532080169381413/1"
  },
  {
    "id": 38,
    "name": "梵云",
    "platform": "QQ",
    "price": 99,
    "publish_time": "4小时内发布",
    "url": "https://www.pxb7.com/product/2091530275881131413/1"
  },
  {
    "id": 39,
    "name": "伐止",
    "platform": "QQ",
    "price": 99,
    "publish_time": "4小时内发布",
    "url": "https://www.pxb7.com/product/2091526920520011413/1"
  },
  {
    "id": 40,
    "name": "玄禾",
    "platform": "QQ",
    "price": 2000,
    "publish_time": "6小时内发布",
    "url": "https://www.pxb7.com/product/2091430703350160230/1"
  },
  {
    "id": 41,
    "name": "玄婳",
    "platform": "QQ",
    "price": 2000,
    "publish_time": "6小时内发布",
    "url": "https://www.pxb7.com/product/2091420469494030230/1"
  },
  {
    "id": 42,
    "name": "玄漪",
    "platform": "QQ",
    "price": 2000,
    "publish_time": "6小时内发布",
    "url": "https://www.pxb7.com/product/2091419043184740230/1"
  },
  {
    "id": 43,
    "name": "刘亦菲",
    "platform": "QQ",
    "price": 200,
    "publish_time": "7小时内发布",
    "url": "https://www.pxb7.com/product/2091308292752067844/1"
  },
  {
    "id": 44,
    "name": "夜神月",
    "platform": "QQ",
    "price": 200,
    "publish_time": "8小时内发布",
    "url": "https://www.pxb7.com/product/2091274822533677844/1"
  },
  {
    "id": 45,
    "name": "圣丹",
    "platform": "QQ",
    "price": 2000,
    "publish_time": "8小时内发布",
    "url": "https://www.pxb7.com/product/2091273291039178667/1"
  },
  {
    "id": 46,
    "name": "侦探",
    "platform": "QQ",
    "price": 2000,
    "publish_time": "8小时内发布",
    "url": "https://www.pxb7.com/product/2091267985736438667/1"
  },
  {
    "id": 47,
    "name": "皇宫",
    "platform": "QQ",
    "price": 2000,
    "publish_time": "8小时内发布",
    "url": "https://www.pxb7.com/product/2091264714261068667/1"
  },
  {
    "id": 48,
    "name": "好女人",
    "platform": "QQ",
    "price": 210,
    "publish_time": "9小时内发布",
    "url": "https://www.pxb7.com/product/2091200792577009690/1"
  },
  {
    "id": 49,
    "name": "襵",
    "platform": "QQ",
    "price": 1888,
    "publish_time": "9小时内发布",
    "url": "https://www.pxb7.com/product/2091195507753569402/1"
  },
  {
    "id": 50,
    "name": "㤲",
    "platform": "QQ",
    "price": 666,
    "publish_time": "9小时内发布",
    "url": "https://www.pxb7.com/product/2091163316306258554/1"
  },
  {
    "id": 51,
    "name": "兰博基尼",
    "platform": "QQ",
    "price": 6999,
    "publish_time": "9小时内发布",
    "url": "https://www.pxb7.com/product/2091149853081813579/1"
  },
  {
    "id": 52,
    "name": "脉",
    "platform": "QQ",
    "price": 9999,
    "publish_time": "10小时内发布",
    "url": "https://www.pxb7.com/product/2091146727669843579/1"
  },
  {
    "id": 53,
    "name": "谢怜妈妈",
    "platform": "微信",
    "price": 60000,
    "publish_time": "10小时内发布",
    "url": "https://www.pxb7.com/product/2091111915520249161/1"
  },
  {
    "id": 54,
    "name": "剂",
    "platform": "QQ",
    "price": 12888,
    "publish_time": "10小时内发布",
    "url": "https://www.pxb7.com/product/2091106777170686823/1"
  },
  {
    "id": 55,
    "name": "谇",
    "platform": "QQ",
    "price": 3499,
    "publish_time": "10小时内发布",
    "url": "https://www.pxb7.com/product/2091105288192336823/1"
  },
  {
    "id": 56,
    "name": "训",
    "platform": "QQ",
    "price": 7999,
    "publish_time": "10小时内发布",
    "url": "https://www.pxb7.com/product/2091102876549156823/1"
  },
  {
    "id": 57,
    "name": "竛",
    "platform": "微信",
    "price": 2388,
    "publish_time": "10小时内发布",
    "url": "https://www.pxb7.com/product/2091101093970466823/1"
  },
  {
    "id": 58,
    "name": "老咩",
    "platform": "QQ",
    "price": 100,
    "publish_time": "10小时内发布",
    "url": "https://www.pxb7.com/product/2091085323879348992/1"
  },
  {
    "id": 59,
    "name": "騙",
    "platform": "QQ",
    "price": 1688,
    "publish_time": "10小时内发布",
    "url": "https://www.pxb7.com/product/2091073516257970212/1"
  },
  {
    "id": 60,
    "name": "鎖",
    "platform": "微信",
    "price": 1988,
    "publish_time": "10小时内发布",
    "url": "https://www.pxb7.com/product/2091072363151540212/1"
  },
  {
    "id": 61,
    "name": "太子浩",
    "platform": "QQ",
    "price": 99999,
    "publish_time": "11小时内发布",
    "url": "https://www.pxb7.com/product/2091069301063784091/1"
  },
  {
    "id": 62,
    "name": "我剑可斩天",
    "platform": "QQ",
    "price": 99999,
    "publish_time": "11小时内发布",
    "url": "https://www.pxb7.com/product/2091064813650514091/1"
  },
  {
    "id": 63,
    "name": "太子昊",
    "platform": "QQ",
    "price": 99999,
    "publish_time": "11小时内发布",
    "url": "https://www.pxb7.com/product/2091059780322004091/1"
  },
  {
    "id": 64,
    "name": "广陵曲",
    "platform": "QQ",
    "price": 99999,
    "publish_time": "11小时内发布",
    "url": "https://www.pxb7.com/product/2091057032479294091/1"
  },
  {
    "id": 65,
    "name": "要抱一下",
    "platform": "QQ",
    "price": 99999,
    "publish_time": "11小时内发布",
    "url": "https://www.pxb7.com/product/2091051748311214091/1"
  },
  {
    "id": 66,
    "name": "爱撩妹",
    "platform": "QQ",
    "price": 1000,
    "publish_time": "11小时内发布",
    "url": "https://www.pxb7.com/product/2091036040643266514/1"
  },
  {
    "id": 67,
    "name": "纯慈/忆忧/老鼠仔",
    "platform": "微信",
    "price": 999999,
    "publish_time": "11小时内发布",
    "url": "https://www.pxb7.com/product/2091033754174098328/1"
  },
  {
    "id": 68,
    "name": "刀斩我心",
    "platform": "QQ",
    "price": 888,
    "publish_time": "11小时内发布",
    "url": "https://www.pxb7.com/product/2091024674242636514/1"
  },
  {
    "id": 69,
    "name": "尽诉心中情",
    "platform": "微信",
    "price": 88,
    "publish_time": "11小时内发布",
    "url": "https://www.pxb7.com/product/2091018990224256514/1"
  },
  {
    "id": 70,
    "name": "瞳孔",
    "platform": "QQ",
    "price": 1888,
    "publish_time": "11小时内发布",
    "url": "https://www.pxb7.com/product/2091016557855474707/1"
  },
  {
    "id": 71,
    "name": "忧郁的公主",
    "platform": "QQ",
    "price": 450,
    "publish_time": "11小时内发布",
    "url": "https://www.pxb7.com/product/2091004520611957503/1"
  },
  {
    "id": 72,
    "name": "地上足球李赣",
    "platform": "QQ",
    "price": 888,
    "publish_time": "12小时内发布",
    "url": "https://www.pxb7.com/product/2090984744223191231/1"
  },
  {
    "id": 73,
    "name": "摧",
    "platform": "QQ",
    "price": 2150,
    "publish_time": "12小时内发布",
    "url": "https://www.pxb7.com/product/2090982227640802313/1"
  },
  {
    "id": 74,
    "name": "肖战女儿",
    "platform": "QQ",
    "price": 10000,
    "publish_time": "12小时内发布",
    "url": "https://www.pxb7.com/product/2090981514199761514/1"
  },
  {
    "id": 75,
    "name": "靛",
    "platform": "QQ",
    "price": 2150,
    "publish_time": "12小时内发布",
    "url": "https://www.pxb7.com/product/2090980968940122313/1"
  },
  {
    "id": 76,
    "name": "ㆶ",
    "platform": "微信",
    "price": 1520,
    "publish_time": "12小时内发布",
    "url": "https://www.pxb7.com/product/2090964275528635355/1"
  },
  {
    "id": 77,
    "name": "小亶",
    "platform": "微信",
    "price": 1314,
    "publish_time": "12小时内发布",
    "url": "https://www.pxb7.com/product/2090962472141125355/1"
  },
  {
    "id": 78,
    "name": "麋失途",
    "platform": "QQ",
    "price": 1000,
    "publish_time": "12小时内发布",
    "url": "https://www.pxb7.com/product/2090962262262673051/1"
  },
  {
    "id": 79,
    "name": "双字ID",
    "platform": "微信",
    "price": 1000,
    "publish_time": "12小时内发布",
    "url": "https://www.pxb7.com/product/2090953538601865341/1"
  },
  {
    "id": 80,
    "name": "双字ID",
    "platform": "QQ",
    "price": 666,
    "publish_time": "12小时内发布",
    "url": "https://www.pxb7.com/product/2090950455869905341/1"
  },
  {
    "id": 81,
    "name": "神 和 帝皇",
    "platform": "QQ",
    "price": 1000,
    "publish_time": "12小时内发布",
    "url": "https://www.pxb7.com/product/2090936173691386809/1"
  },
  {
    "id": 82,
    "name": "王者荣耀世界",
    "platform": "QQ",
    "price": 1200,
    "publish_time": "13小时内发布",
    "url": "https://www.pxb7.com/product/2090920424571062586/1"
  },
  {
    "id": 83,
    "name": "我是克烈",
    "platform": "QQ",
    "price": 18888,
    "publish_time": "13小时内发布",
    "url": "https://www.pxb7.com/product/2090878670111525556/1"
  },
  {
    "id": 84,
    "name": "程女士",
    "platform": "QQ",
    "price": 8888,
    "publish_time": "13小时内发布",
    "url": "https://www.pxb7.com/product/2090870365143805556/1"
  },
  {
    "id": 85,
    "name": "含情说梦",
    "platform": "QQ",
    "price": 100,
    "publish_time": "13小时内发布",
    "url": "https://www.pxb7.com/product/2090864975463100633/1"
  },
  {
    "id": 86,
    "name": "文奇呀",
    "platform": "QQ",
    "price": 50000,
    "publish_time": "14小时内发布",
    "url": "https://www.pxb7.com/product/2090844843459103795/1"
  },
  {
    "id": 87,
    "name": "仙女姐姐",
    "platform": "微信",
    "price": 1888,
    "publish_time": "14小时内发布",
    "url": "https://www.pxb7.com/product/2090815377654287746/1"
  },
  {
    "id": 88,
    "name": "335963",
    "platform": "QQ",
    "price": 5000,
    "publish_time": "14小时内发布",
    "url": "https://www.pxb7.com/product/2090797405225489865/1"
  },
  {
    "id": 89,
    "name": "需",
    "platform": "QQ",
    "price": 1200,
    "publish_time": "14小时内发布",
    "url": "https://www.pxb7.com/product/2090796105400935854/1"
  },
  {
    "id": 90,
    "name": "孕期",
    "platform": "QQ",
    "price": 380,
    "publish_time": "14小时内发布",
    "url": "https://www.pxb7.com/product/2090779411579570633/1"
  },
  {
    "id": 91,
    "name": "多人世界",
    "platform": "微信",
    "price": 80,
    "publish_time": "15小时内发布",
    "url": "https://www.pxb7.com/product/2090773330084702535/1"
  },
  {
    "id": 92,
    "name": "①②③",
    "platform": "QQ",
    "price": 9999,
    "publish_time": "15小时内发布",
    "url": "https://www.pxb7.com/product/2090764123259917442/1"
  },
  {
    "id": 93,
    "name": "热门ID",
    "platform": "QQ",
    "price": 3000,
    "publish_time": "15小时内发布",
    "url": "https://www.pxb7.com/product/2090763557274576276/1"
  },
  {
    "id": 94,
    "name": "⑧⑧⑧⑧⑧⑧",
    "platform": "QQ",
    "price": 9999,
    "publish_time": "15小时内发布",
    "url": "https://www.pxb7.com/product/2090761648620477442/1"
  },
  {
    "id": 95,
    "name": "⑥⑥⑥⑥⑥⑥",
    "platform": "QQ",
    "price": 9999,
    "publish_time": "15小时内发布",
    "url": "https://www.pxb7.com/product/2090758335775667442/1"
  },
  {
    "id": 96,
    "name": "山东宋亚轩",
    "platform": "QQ",
    "price": 99999,
    "publish_time": "15小时内发布",
    "url": "https://www.pxb7.com/product/2090730170777797092/1"
  },
  {
    "id": 97,
    "name": "鸡西",
    "platform": "QQ",
    "price": 666,
    "publish_time": "15小时内发布",
    "url": "https://www.pxb7.com/product/2090729080504821862/1"
  },
  {
    "id": 98,
    "name": "たか",
    "platform": "QQ",
    "price": 666,
    "publish_time": "15小时内发布",
    "url": "https://www.pxb7.com/product/2090727234601849322/1"
  },
  {
    "id": 99,
    "name": "猪笨笨",
    "platform": "微信",
    "price": 666,
    "publish_time": "15小时内发布",
    "url": "https://www.pxb7.com/product/2090719831573321862/1"
  },
  {
    "id": 100,
    "name": "圆润脸",
    "platform": "微信",
    "price": 666,
    "publish_time": "15小时内发布",
    "url": "https://www.pxb7.com/product/2090717084467991862/1"
  }
]